LICENSE
MANIFEST.in
README.rst
requirements.txt
setup.py
kerefcord/__init__.py
kerefcord/__main__.py
kerefcord/abc.py
kerefcord/activity.py
kerefcord/appinfo.py
kerefcord/asset.py
kerefcord/audit_logs.py
kerefcord/backoff.py
kerefcord/channel.py
kerefcord/client.py
kerefcord/colour.py
kerefcord/components.py
kerefcord/context_managers.py
kerefcord/embeds.py
kerefcord/emoji.py
kerefcord/enums.py
kerefcord/errors.py
kerefcord/file.py
kerefcord/flags.py
kerefcord/gateway.py
kerefcord/guild.py
kerefcord/http.py
kerefcord/integrations.py
kerefcord/interactions.py
kerefcord/invite.py
kerefcord/iterators.py
kerefcord/member.py
kerefcord/mentions.py
kerefcord/message.py
kerefcord/mixins.py
kerefcord/object.py
kerefcord/oggparse.py
kerefcord/opus.py
kerefcord/partial_emoji.py
kerefcord/permissions.py
kerefcord/player.py
kerefcord/raw_models.py
kerefcord/reaction.py
kerefcord/role.py
kerefcord/shard.py
kerefcord/stage_instance.py
kerefcord/state.py
kerefcord/sticker.py
kerefcord/team.py
kerefcord/template.py
kerefcord/threads.py
kerefcord/user.py
kerefcord/utils.py
kerefcord/voice_client.py
kerefcord/widget.py
kerefcord.egg-info/PKG-INFO
kerefcord.egg-info/SOURCES.txt
kerefcord.egg-info/dependency_links.txt
kerefcord.egg-info/requires.txt
kerefcord.egg-info/top_level.txt
kerefcord/ext/commands/__init__.py
kerefcord/ext/commands/_types.py
kerefcord/ext/commands/bot.py
kerefcord/ext/commands/cog.py
kerefcord/ext/commands/context.py
kerefcord/ext/commands/converter.py
kerefcord/ext/commands/cooldowns.py
kerefcord/ext/commands/core.py
kerefcord/ext/commands/errors.py
kerefcord/ext/commands/flags.py
kerefcord/ext/commands/help.py
kerefcord/ext/commands/view.py
kerefcord/ext/tasks/__init__.py
kerefcord/types/__init__.py
kerefcord/types/activity.py
kerefcord/types/appinfo.py
kerefcord/types/audit_log.py
kerefcord/types/channel.py
kerefcord/types/components.py
kerefcord/types/embed.py
kerefcord/types/emoji.py
kerefcord/types/gateway.py
kerefcord/types/guild.py
kerefcord/types/integration.py
kerefcord/types/interactions.py
kerefcord/types/invite.py
kerefcord/types/member.py
kerefcord/types/message.py
kerefcord/types/raw_models.py
