Metadata-Version: 2.1
Name: kerefcord
Version: 3.0a6
Summary: A Python wrapper for the kerefcord API
Home-page: https://github.com/Kerefkerefcord/kerefcord.py
Author: Keref
License: MIT
Project-URL: Documentation, https://kerefcordpy.readthedocs.io/en/latest/
Project-URL: Issue tracker, https://github.com/Kerefkerefcord/discrap.py/issues
Platform: UNKNOWN
Classifier: Development Status :: 5 - Production/Stable
Classifier: License :: OSI Approved :: MIT License
Classifier: Intended Audience :: Developers
Classifier: Natural Language :: English
Classifier: Operating System :: OS Independent
Classifier: Programming Language :: Python :: 3.8
Classifier: Programming Language :: Python :: 3.9
Classifier: Topic :: Internet
Classifier: Topic :: Software Development :: Libraries
Classifier: Topic :: Software Development :: Libraries :: Python Modules
Classifier: Topic :: Utilities
Classifier: Typing :: Typed
Requires-Python: >=3.8.0
Provides-Extra: docs
Provides-Extra: speed
Provides-Extra: voice
